CHANGES.txt
CONTRIBUTORS.txt
MANIFEST.in
README.txt
setup.py
docs/HISTORY.txt
docs/INSTALL.txt
docs/LICENSE.GPL
docs/LICENSE.txt
genericsetup/__init__.py
genericsetup.quickinstaller.egg-info/PKG-INFO
genericsetup.quickinstaller.egg-info/SOURCES.txt
genericsetup.quickinstaller.egg-info/dependency_links.txt
genericsetup.quickinstaller.egg-info/namespace_packages.txt
genericsetup.quickinstaller.egg-info/not-zip-safe
genericsetup.quickinstaller.egg-info/requires.txt
genericsetup.quickinstaller.egg-info/top_level.txt
genericsetup/quickinstaller/README.txt
genericsetup/quickinstaller/__init__.py
genericsetup/quickinstaller/configure.zcml
genericsetup/quickinstaller/products.py
genericsetup/quickinstaller/interfaces/__init__.py
genericsetup/quickinstaller/tests/__init__.py
genericsetup/quickinstaller/tests/base.py
genericsetup/quickinstaller/tests/test_doctest.py