Metadata-Version: 1.0
Name: genericsetup.quickinstaller
Version: 0.2
Summary: Import step to install products (without profile) in QuickInstaller
Home-page: http://svn.plone.org/svn/collective/genericsetup.quickinstaller
Author: KULeuven ICTS
Author-email: wms@icts.kuleuven.be
License: GPL
Platform: UNKNOWN
Classifier: Framework :: Plone
Classifier: Intended Audience :: Developers
Classifier: Topic :: Software Development :: Libraries :: Python Modules
Classifier: License :: OSI Approved :: GNU General Public License (GPL)
